promptweaver-0.1.16.dist-info/METADATA
promptweaver-0.1.16.dist-info/WHEEL
promptweaver-0.1.16.dist-info/entry_points.txt
promptweaver-0.1.16.dist-info/licenses/LICENSE
promptweaver/__init__.py
promptweaver/clients/__init__.py
promptweaver/clients/gemini/__init__.py
promptweaver/clients/gemini/gemini_client.py
promptweaver/clients/gemini/multimodal_content_builder.py
promptweaver/core/__init__.py
promptweaver/core/base_llm_client.py
promptweaver/core/content_builder.py
promptweaver/core/prompt_template.py
promptweaver/utils/__init__.py
promptweaver/utils/mime_utils.py
promptweaver/utils/string_utils.py
promptweaver-0.1.16.dist-info/RECORD
