Metadata-Version: 2.1
Name: promptweaver
Version: 0.1.16
Summary: PromptWeaver streamlines prompt development and management in Generative AI workflows
Author-Email: Gen AI Solution Accelerators <gen-ai-solution-accelerators@google.com>
License: Apache-2.0
Requires-Python: >=3.9
Requires-Dist: jinja2>=3.1.4
Requires-Dist: pyyaml>=6.0.1
Requires-Dist: google-cloud-aiplatform
